password_credentials/__init__.py
password_credentials/credentials.py
password_credentials-0.0.6.dist-info/LICENSE
password_credentials-0.0.6.dist-info/METADATA
password_credentials-0.0.6.dist-info/WHEEL
password_credentials-0.0.6.dist-info/top_level.txt
password_credentials-0.0.6.dist-info/RECORD
