Metadata-Version: 2.1
Name: password-credentials
Version: 0.0.6
Summary: Generate username and password credentials.
Home-page: https://github.com/SanteriHetekivi/password_credentials
Author: Santeri Hetekivi
Author-email: development@hetekivi.com
Project-URL: Bug Tracker, https://github.com/SanteriHetekivi/password_credentials/issues
Classifier: Programming Language :: Python :: 3
Classifier: License :: OSI Approved :: Apache Software License
Classifier: Operating System :: OS Independent
Requires-Python: >=3.10
License-File: LICENSE
